<annotation verified="no">
  <folder>i3</folder>
  <filename>9.jpg</filename>
  <path>/mnt/c/Users/Minith/Documents/darkflow-master/i3/9.jpg</path>
  <source>
    <database>Unknown</database>
  </source>
  <size>
    <width>480</width>
    <height>640</height>
    <depth>3</depth>
  </size>
  <segmented>0</segmented>
  <object>
    <name>shirt</name>
    <pose>Unspecified</pose>
    <truncated>0</truncated>
    <difficult>0</difficult>
    <bndbox>
      <xmin>134</xmin>
      <ymin>94</ymin>
      <xmax>309</xmax>
      <ymax>299</ymax>
    </bndbox>
  </object>
  <object>
    <name>jeans</name>
    <pose>Unspecified</pose>
    <truncated>0</truncated>
    <difficult>0</difficult>
    <bndbox>
      <xmin>145</xmin>
      <ymin>302</ymin>
      <xmax>268</xmax>
      <ymax>552</ymax>
    </bndbox>
  </object>
</annotation>
